Split_Excel_Package/__init__.py
Split_Excel_Package/excel_splitter.py
excel_splitter-0.6.dist-info/METADATA
excel_splitter-0.6.dist-info/WHEEL
excel_splitter-0.6.dist-info/top_level.txt
excel_splitter-0.6.dist-info/RECORD
