Metadata-Version: 2.1
Name: excel-splitter
Version: 0.6
Home-page: https://github.com/Guitarman-Waiting-In-The-Sky/excel_splitter
Author: Jason Yearry
Author-email: jasonyearry@gmail.com
License: MIT
Keywords: Excel,Split,opensource
Requires-Dist: openpyxl (>=3.0.10)
